cantus/__init__.py
cantus-0.0.0.dist-info/METADATA
cantus-0.0.0.dist-info/WHEEL
cantus-0.0.0.dist-info/top_level.txt
cantus-0.0.0.dist-info/RECORD
