Metadata-Version: 2.1
Name: cantus
Version: 0.0.0
Summary: Coming soon
Author-email: Tim Eipert <tim.eipert@uni-wuerzburg.de>
